{
	"backtraceGraph" : 
	{
		"commands" : 
		[
			"install"
		],
		"files" : 
		[
			"Source/CMakeLists.txt"
		],
		"nodes" : 
		[
			{
				"file" : 0
			},
			{
				"command" : 0,
				"file" : 0,
				"line" : 35,
				"parent" : 0
			}
		]
	},
	"installers" : 
	[
		{
			"backtrace" : 1,
			"component" : "Unspecified",
			"destination" : "lib",
			"paths" : 
			[
				"Source/libConflux.a"
			],
			"targetId" : "Conflux::@43690dd2fb94c8e45e84",
			"targetIndex" : 0,
			"type" : "target"
		},
		{
			"backtrace" : 1,
			"component" : "Unspecified",
			"destination" : "include",
			"fileSetDirectories" : 
			[
				"include"
			],
			"fileSetName" : "HEADERS",
			"fileSetTarget" : 
			{
				"id" : "Conflux::@43690dd2fb94c8e45e84",
				"index" : 0
			},
			"fileSetType" : "HEADERS",
			"paths" : 
			[
				{
					"from" : "include/Conflux/Memory.hxx",
					"to" : "Conflux/Memory.hxx"
				},
				{
					"from" : "include/Conflux/Utils.hxx",
					"to" : "Conflux/Utils.hxx"
				}
			],
			"type" : "fileSet"
		}
	],
	"paths" : 
	{
		"build" : "Source",
		"source" : "Source"
	}
}
